MANIFEST.in
setup.py
hebo_tools/__init__.py
hebo_tools/logging_config.py
hebo_tools/status_tool.py
hebo_tools/version.py
hebo_tools.egg-info/PKG-INFO
hebo_tools.egg-info/SOURCES.txt
hebo_tools.egg-info/dependency_links.txt
hebo_tools.egg-info/top_level.txt